dastools/__init__.py
dastools/basemodels.py
dastools/core.py
dastools/utils.py
dastools/app/__init__.py
dastools/app/dasconv.py
dastools/app/dasmetadata.py
dastools/app/json2stationxml.py
dastools/app/test_dasconv.py
dastools/app/test_dasmetadata.py
dastools/data/datacite.xml
dastools/data/dataselect.wadl
dastools/data/station.wadl
dastools/data/filters/fir235.txt
dastools/input/__init__.py
dastools/input/das.py
dastools/input/febus.py
dastools/input/optasense.py
dastools/input/optodas.py
dastools/input/tdms.py
dastools/input/test_febus.py
dastools/input/test_optodas.py
dastools/input/test_tdms.py
dastools/output/__init__.py
dastools/output/archive.py
dastools/output/test_archive.py
dastools/partition/__init__.py
dastools/partition/parallelization.py
dastools/server/__init__.py
dastools/server/dasws.py
dastools/server/tdmsws.py
dastools/server/test_dasws.py
dastools-0.9.6.post2.dist-info/licenses/AUTHORS
dastools-0.9.6.post2.dist-info/licenses/COPYING
dastools-0.9.6.post2.dist-info/licenses/LICENSE
dastools-0.9.6.post2.dist-info/METADATA
dastools-0.9.6.post2.dist-info/WHEEL
dastools-0.9.6.post2.dist-info/entry_points.txt
dastools-0.9.6.post2.dist-info/top_level.txt
dastools-0.9.6.post2.dist-info/RECORD
