Metadata-Version: 2.4
Name: dastools
Version: 0.9.6.post2
Summary: dastools: Tools to work with data generated by DAS systems
Home-page: https://git.gfz-potsdam.de/javier/dastools
Author: Javier Quinteros
Author-email: javier@gfz.de
License: GPLv3
Keywords: seismology DAS waveforms fdsnws dataselect
Classifier: Development Status :: 5 - Production/Stable
Classifier: Environment :: Console
Classifier: Framework :: FastAPI
Classifier: Intended Audience :: Science/Research
Classifier: License :: OSI Approved :: GNU General Public License v3 or later (GPLv3+)
Classifier: Natural Language :: English
Classifier: Operating System :: POSIX :: Linux
Classifier: Operating System :: MacOS
Classifier: Programming Language :: Python :: 3
Classifier: Programming Language :: Python :: 3.8
Classifier: Programming Language :: Python :: 3.9
Classifier: Programming Language :: Python :: 3.10
Classifier: Programming Language :: Python :: 3.11
Classifier: Programming Language :: Python :: 3.12
Classifier: Topic :: Internet :: WWW/HTTP :: WSGI
Classifier: Topic :: Internet :: WWW/HTTP :: WSGI :: Application
Classifier: Topic :: Internet :: WWW/HTTP :: WSGI :: Middleware
Classifier: Topic :: Scientific/Engineering
Provides: dastools
Requires-Python: >=3
License-File: LICENSE
License-File: COPYING
License-File: AUTHORS
Requires-Dist: obspy
Requires-Dist: numpy
Requires-Dist: scipy
Requires-Dist: fastapi
Requires-Dist: uvicorn
Requires-Dist: pydantic>=2
Requires-Dist: tqdm
Requires-Dist: h5py
Requires-Dist: pytest-cov
Requires-Dist: httpx
Requires-Dist: click
Requires-Dist: jinja2
Requires-Dist: sphinx
Requires-Dist: jsonschema
Dynamic: author
Dynamic: author-email
Dynamic: classifier
Dynamic: description
Dynamic: home-page
Dynamic: keywords
Dynamic: license
Dynamic: license-file
Dynamic: provides
Dynamic: requires-dist
Dynamic: requires-python
Dynamic: summary
